mypy-stubs/bs4/__init__.pyi
mypy-stubs/bs4/element.pyi
mypy-stubs/mechanicalsoup/__init__.pyi
mypy-stubs/mechanicalsoup/browser.pyi
mypy-stubs/mechanicalsoup/form.pyi
mypy-stubs/mechanicalsoup/stateful_browser.pyi
wilmes/__init__.py
wilmes/__main__.py
wilmes/_bs_utils.py
wilmes/_client.py
wilmes/_email_unmangling.py
wilmes/_emojis.py
wilmes/_settings.py
wilmes/_types.py
wilmes/py.typed
wilmes/tests/test_email_unmangling.py
wilmes-0.11.2.dist-info/LICENSE
wilmes-0.11.2.dist-info/METADATA
wilmes-0.11.2.dist-info/WHEEL
wilmes-0.11.2.dist-info/entry_points.txt
wilmes-0.11.2.dist-info/top_level.txt
wilmes-0.11.2.dist-info/RECORD
