Metadata-Version: 2.1
Name: wilmes
Version: 0.11.2
Summary: Message fetching library for a Finnish school site
Author-email: Tuomas Suutari <tuomas@nepnep.net>
License: MIT License
Project-URL: Homepage, https://github.com/suutari/wilmes
Project-URL: Repository, https://github.com/suutari/wilmes
Classifier: Development Status :: 4 - Beta
Classifier: Intended Audience :: Developers
Classifier: License :: OSI Approved :: MIT License
Classifier: Programming Language :: Python :: 3
Classifier: Topic :: Communications
Classifier: Topic :: Software Development :: Libraries
Requires-Python: >=3.6
License-File: LICENSE
Requires-Dist: mechanicalsoup >=0.8
Requires-Dist: python-dateutil >=2.0
Requires-Dist: pytz
Provides-Extra: dev
Requires-Dist: mypy ; extra == 'dev'
Requires-Dist: types-pytz ; extra == 'dev'
Requires-Dist: types-requests ; extra == 'dev'
Requires-Dist: types-python-dateutil ; extra == 'dev'
Requires-Dist: flake8 ; extra == 'dev'
Requires-Dist: flake8-isort ; extra == 'dev'
Requires-Dist: pep8-naming ; extra == 'dev'
Requires-Dist: ipython ; extra == 'dev'
Requires-Dist: jedi ; extra == 'dev'
